wcpan/drive/core/__init__.py
wcpan/drive/core/_drive.py
wcpan/drive/core/_lib.py
wcpan/drive/core/exceptions.py
wcpan/drive/core/lib.py
wcpan/drive/core/py.typed
wcpan/drive/core/types.py
wcpan_drive_core-4.2.0.dist-info/LICENSE.txt
wcpan_drive_core-4.2.0.dist-info/METADATA
wcpan_drive_core-4.2.0.dist-info/WHEEL
wcpan_drive_core-4.2.0.dist-info/RECORD
